nodejs_console_log/__init__.py
nodejs_console_log/log.py
Nodejs_Console_Log-0.1.dist-info/LICENSE
Nodejs_Console_Log-0.1.dist-info/METADATA
Nodejs_Console_Log-0.1.dist-info/WHEEL
Nodejs_Console_Log-0.1.dist-info/top_level.txt
Nodejs_Console_Log-0.1.dist-info/RECORD
